setup.py
excelpy.egg-info/PKG-INFO
excelpy.egg-info/SOURCES.txt
excelpy.egg-info/dependency_links.txt
excelpy.egg-info/requires.txt
excelpy.egg-info/top_level.txt
src/excelpy/__init__.py
src/excelpy/excelpy.py
src/excelpy/test.py
src/excelpy/test_excelpy.py
src/excelpy/xlsx_ns.py
src/excelpy/templates/__init__.py
src/excelpy/templates/xl
src/excelpy/templates/xl/worksheets
src/excelpy/templates/xl/worksheets/__init__.py
src/excelpy/templates/xl/worksheets/sheet.xml