Metadata-Version: 1.1
Name: excelpy
Version: 0.1.3.5
Summary: Minimal Microsoft Excel 2010 library for Python 3.3. 
Home-page: https://github.com/dokenzy/excelpy
Author: dokenzy
Author-email: dokenzy@gmail.com
License: MIT License
Keywords: xlsx,excel,spreadsheet
Platform: UNKNOWN
Classifier: Development Status :: 3 - Alpha
Classifier: Intended Audience :: Developers
Classifier: License :: OSI Approved :: MIT License
Classifier: Programming Language :: Python
Classifier: Programming Language :: Python :: 3
Classifier: Operating System :: OS Independent
Classifier: Topic :: Database
Classifier: Topic :: Office/Business
Classifier: Topic :: Software Development :: Libraries :: Python Modules
